LICENSE
MANIFEST.in
README.md
setup.py
qhub_jupyterhub_theme/__init__.py
qhub_jupyterhub_theme.egg-info/PKG-INFO
qhub_jupyterhub_theme.egg-info/SOURCES.txt
qhub_jupyterhub_theme.egg-info/dependency_links.txt
qhub_jupyterhub_theme.egg-info/requires.txt
qhub_jupyterhub_theme.egg-info/top_level.txt
qhub_jupyterhub_theme/custom/css/panton.black-caps.otf
qhub_jupyterhub_theme/custom/css/panton.light-caps.otf
qhub_jupyterhub_theme/custom/images/jupyter_qhub_logo.svg
qhub_jupyterhub_theme/custom/images/jupyter_qhub_logo_small.png
qhub_jupyterhub_theme/templates/login.html
qhub_jupyterhub_theme/templates/page.html
qhub_jupyterhub_theme/templates/style.css