Metadata-Version: 2.1
Name: qhub-jupyterhub-theme
Version: 0.3.2
Summary: QHub jupyterhub theme
Home-page: https://github.com/Quansight/qhub-jupyterhub-theme
Author: Quansight
License: UNKNOWN
Project-URL: Bug Reports, https://github.com/Quansight/qhub-jupyterhub-theme
Project-URL: Source, https://github.com/Quansight/qhub-jupyterhub-theme
Keywords: jupyterhub theme
Platform: UNKNOWN
Classifier: Development Status :: 3 - Alpha
Classifier: Intended Audience :: Developers
Classifier: Topic :: Software Development :: Build Tools
Classifier: Programming Language :: Python :: 3
Classifier: Programming Language :: Python :: 3.6
Classifier: Programming Language :: Python :: 3.7
Classifier: Programming Language :: Python :: 3.8
Requires-Python: !=3.0.*, !=3.1.*, !=3.2.*, !=3.3.*, !=3.4.*, !=3.5.*, <4
